gentopia/__init__.py
gentopia/agent/__init__.py
gentopia/agent/base_agent.py
gentopia/agent/plugin_manager.py
gentopia/agent/openai/__init__.py
gentopia/agent/openai/agent.py
gentopia/agent/openai_memory/__init__.py
gentopia/agent/openai_memory/agent.py
gentopia/agent/openai_memory/load_memory.py
gentopia/agent/react/__init__.py
gentopia/agent/react/agent.py
gentopia/agent/rewoo/__init__.py
gentopia/agent/rewoo/agent.py
gentopia/agent/rewoo/nodes/Planner.py
gentopia/agent/rewoo/nodes/Solver.py
gentopia/agent/rewoo/nodes/__init__.py
gentopia/agent/vanilla/__init__.py
gentopia/agent/vanilla/agent.py
gentopia/assembler/__init__.py
gentopia/assembler/agent_assembler.py
gentopia/assembler/config.py
gentopia/assembler/loader.py
gentopia/assembler/task.py
gentopia/llm/__init__.py
gentopia/llm/base_llm.py
gentopia/llm/llm_info.py
gentopia/llm/test_llm.py
gentopia/llm/wrap_llm.py
gentopia/llm/client/__init__.py
gentopia/llm/client/huggingface.py
gentopia/llm/client/openai.py
gentopia/llm/loaders/__init__.py
gentopia/llm/loaders/airoboros.py
gentopia/llm/loaders/alpaca.py
gentopia/llm/loaders/baize.py
gentopia/llm/loaders/bloom.py
gentopia/llm/loaders/camel.py
gentopia/llm/loaders/falcon.py
gentopia/llm/loaders/flan_alpaca.py
gentopia/llm/loaders/guanaco.py
gentopia/llm/loaders/kullm.py
gentopia/llm/loaders/mpt.py
gentopia/llm/loaders/redpajama.py
gentopia/llm/loaders/replit.py
gentopia/llm/loaders/samantha_vicuna.py
gentopia/llm/loaders/stablelm.py
gentopia/llm/loaders/starchat.py
gentopia/llm/loaders/t5_vicuna.py
gentopia/llm/loaders/vicuna.py
gentopia/manager/__init__.py
gentopia/manager/base_llm_manager.py
gentopia/manager/local_llm_manager.py
gentopia/manager/server_info.py
gentopia/manager/llm_client/__init__.py
gentopia/manager/llm_client/base_llm_client.py
gentopia/manager/llm_client/local_llm_client.py
gentopia/memory/__init__.py
gentopia/memory/api.py
gentopia/memory/base_memory.py
gentopia/memory/document.py
gentopia/memory/embeddings.py
gentopia-0.0.4.dist-info/LICENSE
gentopia-0.0.4.dist-info/METADATA
gentopia-0.0.4.dist-info/WHEEL
gentopia-0.0.4.dist-info/top_level.txt
gentopia-0.0.4.dist-info/RECORD
