Metadata-Version: 2.1
Name: gentopia
Version: 0.0.4
Summary: Gentopia provides extensive utilities to assembles ALM agents driven by configs.
Home-page: https://github.com/Gentopia-AI/Gentopia
Author: billxbf
Author-email: billxbf@gmail.com
License: MIT license
License-File: LICENSE
Requires-Dist: tenacity
Requires-Dist: python-dotenv
Requires-Dist: arxiv
Requires-Dist: chardet
Requires-Dist: cchardet
Requires-Dist: numexpr
Requires-Dist: googlesearch-python
Requires-Dist: wolframalpha
Requires-Dist: numpy
Requires-Dist: rich
Requires-Dist: tqdm
Requires-Dist: prompt-toolkit
Requires-Dist: regex
Requires-Dist: attrs
Requires-Dist: fastapi
Requires-Dist: geopy
Requires-Dist: pydantic (==1.9)
Requires-Dist: pytest
Requires-Dist: PyYAML
Requires-Dist: requests
Requires-Dist: setuptools
Requires-Dist: uvicorn
Requires-Dist: openai
Requires-Dist: pexpect
Requires-Dist: gradio-client
Requires-Dist: pinecone-client
Requires-Dist: chroma
Requires-Dist: chromadb
Requires-Dist: tiktoken
Requires-Dist: scholarly
Provides-Extra: huggingface
Requires-Dist: torch ; extra == 'huggingface'
Requires-Dist: transformers ; extra == 'huggingface'
Requires-Dist: optimum ; extra == 'huggingface'
Requires-Dist: peft ; extra == 'huggingface'
